{"title":"Combined feed","url":"https://TicketOpen.github.io/ticketlink/all.xml","elements":[{"title":"[단독판매] 클래식 & 락 심포니 - 대구 티켓오픈 안내 (티켓링크)","contents":"<em>오픈</em>: 2024.04.05(금) 01:00","link":"http://www.ticketlink.co.kr/help/notice/59173","retrieved":1712191520332},{"title":"[단독판매] 에프게니 미하일로프 초청 연주회 - 대구 티켓오픈 안내 (티켓링크)","contents":"<em>오픈</em>: 2024.04.05(금) 01:00","link":"http://www.ticketlink.co.kr/help/notice/59172","retrieved":1712191520335},{"title":"김동하 크라우드 워크 (Crowd Work) in 대구 티켓오픈 안내 (티켓링크)","contents":"<em>오픈</em>: 2024.04.05(금) 01:00","link":"http://www.ticketlink.co.kr/help/notice/59171","retrieved":1712191520338},{"title":"원더매직의 <오리지널 과학마술콘서트 시즌2>-수원​ 티켓오픈 안내 (티켓링크)","contents":"<em>오픈</em>: 2024.04.04(목) 05:00","link":"http://www.ticketlink.co.kr/help/notice/59170","retrieved":1712131994160},{"title":"마술사 최형배의 <오리지널과학마술콘서트 시즌1>-부평​ 티켓오픈 안내 (티켓링크)","contents":"<em>오픈</em>: 2024.04.04(목) 05:00","link":"http://www.ticketlink.co.kr/help/notice/59169","retrieved":1712131994160},{"title":"​포켓몬 애니메이션 콘서트​ 티켓오픈 안내 (티켓링크)","contents":"<em>오픈</em>: 2024.04.05(금) 05:00","link":"http://www.ticketlink.co.kr/help/notice/59168","retrieved":1712124788703},{"title":"​2024년 금난새x뉴월드챔버오케스트라 콘서트 ‘​가족을 담다’​ 티켓 오픈 안내​ 티켓오픈 안내 (티켓링크)","contents":"<em>오픈</em>: 2024.04.05(금) 05:00","link":"http://www.ticketlink.co.kr/help/notice/59167","retrieved":1712121036227},{"title":"​뮤지컬 일 테노레 (IL TENORE) 마지막 티켓오픈 안내 (티켓링크)","contents":"<em>오픈</em>: 2024.04.08(월) 05:00","link":"http://www.ticketlink.co.kr/help/notice/59166","retrieved":1712121036228},{"title":"​뷰티풀칠드런스데이 with 뷰티풀데이​ 티켓오픈 안내 (티켓링크)","contents":"<em>오픈</em>: 2024.04.05(금) 01:00","link":"http://www.ticketlink.co.kr/help/notice/59165","retrieved":1712121036228},{"title":"[단독판매] 2024 중국진출 한국 프리뷰 공연 / 뮤지컬<제시카>​ 티켓오픈 안내 (티켓링크)","contents":"<em>오픈</em>: 2024.04.04(목) 02:00","link":"http://www.ticketlink.co.kr/help/notice/59164","retrieved":1712113921687},{"title":"[단독판매] 2024년 밤의 석조전 티켓오픈 안내 (티켓링크)","contents":"<em>오픈</em>: 2024.04.05(금) 05:00","link":"http://www.ticketlink.co.kr/help/notice/59163","retrieved":1712108659555},{"title":"뮤지컬 한글용사 아이야 <사라진 한글을 찾아라!> - 청주​​ 티켓오픈 안내 (티켓링크)","contents":"<em>오픈</em>: 2024.04.05(금) 00:00","link":"http://www.ticketlink.co.kr/help/notice/59162","retrieved":1712105003266},{"title":"[단독판매]  ​(2024 대백프라자) 벌룬매직쇼​ 티켓오픈 안내 (티켓링크)","contents":"<em>오픈</em>: 2024.04.05(금) 00:00","link":"http://www.ticketlink.co.kr/help/notice/59161","retrieved":1712105003272},{"title":"[단독판매] 탭댄스쇼 <올 댓 리듬> - 울산​ 티켓오픈 안내 (티켓링크)","contents":"<em>오픈</em>: 2024.04.11(목) 12:00","link":"http://www.ticketlink.co.kr/help/notice/59160","retrieved":1712041908451},{"title":"2024 스카 페스티벌 - 창원 < HIPHOP Super-Swag >​​​​ 티켓오픈 안내 (티켓링크)","contents":"<em>오픈</em>: 2024.04.04(목) 08:00","link":"http://www.ticketlink.co.kr/help/notice/59159","retrieved":1712045625281},{"title":"[단독판매] 클래식 & 락 심포니 - 대구 티켓오픈 안내 (티켓링크 모바일)","contents":"2024.04.05(금) 01:00","link":"http://m.ticketlink.co.kr/help/notice/59173","retrieved":1712191528403},{"title":"[단독판매] 에프게니 미하일로프 초청 연주회 - 대구 티켓오픈 안내 (티켓링크 모바일)","contents":"2024.04.05(금) 01:00","link":"http://m.ticketlink.co.kr/help/notice/59172","retrieved":1712191528406},{"title":"김동하 크라우드 워크 (Crowd Work) in 대구 티켓오픈 안내 (티켓링크 모바일)","contents":"2024.04.05(금) 01:00","link":"http://m.ticketlink.co.kr/help/notice/59171","retrieved":1712191528408},{"title":"원더매직의 <오리지널 과학마술콘서트 시즌2>-수원​ 티켓오픈 안내 (티켓링크 모바일)","contents":"2024.04.04(목) 05:00","link":"http://m.ticketlink.co.kr/help/notice/59170","retrieved":1712132001704},{"title":"마술사 최형배의 <오리지널과학마술콘서트 시즌1>-부평​ 티켓오픈 안내 (티켓링크 모바일)","contents":"2024.04.04(목) 05:00","link":"http://m.ticketlink.co.kr/help/notice/59169","retrieved":1712132001704},{"title":"​포켓몬 애니메이션 콘서트​ 티켓오픈 안내 (티켓링크 모바일)","contents":"2024.04.05(금) 05:00","link":"http://m.ticketlink.co.kr/help/notice/59168","retrieved":1712124795008},{"title":"​2024년 금난새x뉴월드챔버오케스트라 콘서트 ‘​가족을 담다’​ 티켓 오픈 안내​ 티켓오픈 안내 (티켓링크 모바일)","contents":"2024.04.05(금) 05:00","link":"http://m.ticketlink.co.kr/help/notice/59167","retrieved":1712121044309},{"title":"​뮤지컬 일 테노레 (IL TENORE) 마지막 티켓오픈 안내 (티켓링크 모바일)","contents":"2024.04.08(월) 05:00","link":"http://m.ticketlink.co.kr/help/notice/59166","retrieved":1712121044310},{"title":"​뷰티풀칠드런스데이 with 뷰티풀데이​ 티켓오픈 안내 (티켓링크 모바일)","contents":"2024.04.05(금) 01:00","link":"http://m.ticketlink.co.kr/help/notice/59165","retrieved":1712121044310},{"title":"[단독판매] 2024 중국진출 한국 프리뷰 공연 / 뮤지컬<제시카>​ 티켓오픈 안내 (티켓링크 모바일)","contents":"2024.04.04(목) 02:00","link":"http://m.ticketlink.co.kr/help/notice/59164","retrieved":1712113929879},{"title":"[단독판매] 2024년 밤의 석조전 티켓오픈 안내 (티켓링크 모바일)","contents":"2024.04.05(금) 05:00","link":"http://m.ticketlink.co.kr/help/notice/59163","retrieved":1712108667852},{"title":"뮤지컬 한글용사 아이야 <사라진 한글을 찾아라!> - 청주​​ 티켓오픈 안내 (티켓링크 모바일)","contents":"2024.04.05(금) 00:00","link":"http://m.ticketlink.co.kr/help/notice/59162","retrieved":1712105011191},{"title":"[단독판매]  ​(2024 대백프라자) 벌룬매직쇼​ 티켓오픈 안내 (티켓링크 모바일)","contents":"2024.04.05(금) 00:00","link":"http://m.ticketlink.co.kr/help/notice/59161","retrieved":1712105011191},{"title":"[단독판매] 탭댄스쇼 <올 댓 리듬> - 울산​ 티켓오픈 안내 (티켓링크 모바일)","contents":"2024.04.11(목) 12:00","link":"http://m.ticketlink.co.kr/help/notice/59160","retrieved":1712041916246},{"title":"2024 스카 페스티벌 - 창원 < HIPHOP Super-Swag >​​​​ 티켓오픈 안내 (티켓링크 모바일)","contents":"2024.04.04(목) 08:00","link":"http://m.ticketlink.co.kr/help/notice/59159","retrieved":1712045631703}]}