{"title":"Combined feed","url":"https://TicketOpen.github.io/ticketlink/all.xml","elements":[{"title":"[단독판매] 광주시립국악관현악단 제 129회 정기연주회 `청소년 협연의 밤'​ 티켓오픈 안내 (티켓링크)","contents":"<em>오픈</em>: 2022.05.30(월) 01:00","link":"http://www.ticketlink.co.kr/help/notice/54601","retrieved":1653721907543},{"title":"세종 어린이 시리즈 Ⅱ 가족음악극 〈백조마을의 차이콥스키〉 ​​​​​​​​티켓오픈 안내 (티켓링크)","contents":"<em>오픈</em>: 2022.06.03(금) 07:00","link":"http://www.ticketlink.co.kr/help/notice/54600","retrieved":1653639743965},{"title":"뮤지컬 〈유진과 유진〉 2차 티켓오픈 안내​ (티켓링크)","contents":"<em>오픈</em>: 2022.06.03(금) 06:00","link":"http://www.ticketlink.co.kr/help/notice/54599","retrieved":1653632197166},{"title":"강릉시립합창단 제 107회 정기연주회​ 티켓오픈 안내 (티켓링크)","contents":"<em>오픈</em>: 2022.05.30(월) 02:00","link":"http://www.ticketlink.co.kr/help/notice/54598","retrieved":1653632197168},{"title":"[단독판매]   제1회 드림콘서트 트롯 티켓오픈 안내 (티켓링크)","contents":"<em>오픈</em>: 2022.05.31(화) 11:00","link":"http://www.ticketlink.co.kr/help/notice/54597","retrieved":1653628667908},{"title":"뮤지컬 〈은밀하게 위대하게：THE LAST〉 마지막 티켓오픈 안내 (티켓링크)","contents":"<em>오픈</em>: 2022.05.31(화) 02:00","link":"http://www.ticketlink.co.kr/help/notice/54596","retrieved":1653628667910},{"title":"가족뮤지컬[반짝반짝 달님이의 버블버블 솜사탕] ​​​​​​​​티켓오픈 안내 (티켓링크)","contents":"<em>오픈</em>: 2022.05.31(화) 01:00","link":"http://www.ticketlink.co.kr/help/notice/54595","retrieved":1653628667912},{"title":"엘사의 생일파티 - 이천 ​​​​​​​​티켓오픈 안내 (티켓링크)","contents":"<em>오픈</em>: 2022.05.31(화) 00:00","link":"http://www.ticketlink.co.kr/help/notice/54594","retrieved":1653628667913},{"title":"헬로카봇 뮤지컬 시즌6 <흔들흔들 댄스파티> - 인천 ​​​​​​​​티켓오픈 안내 (티켓링크)","contents":"<em>오픈</em>: 2022.06.02(목) 02:00","link":"http://www.ticketlink.co.kr/help/notice/54593","retrieved":1653628667915},{"title":"엘사의 생일파티 - 서산 ​​​​​​​​티켓오픈 안내 (티켓링크)","contents":"<em>오픈</em>: 2022.06.02(목) 00:00","link":"http://www.ticketlink.co.kr/help/notice/54592","retrieved":1653628667916},{"title":"뮤지컬 <타루와리나> ​​​​​​​​티켓오픈 안내 (티켓링크)","contents":"<em>오픈</em>: 2022.05.31(화) 05:00","link":"http://www.ticketlink.co.kr/help/notice/54591","retrieved":1653628667917},{"title":"엘사의 생일파티 - 대구 동구 ​​​​​​​​티켓오픈 안내 (티켓링크)","contents":"<em>오픈</em>: 2022.06.02(목) 00:00","link":"http://www.ticketlink.co.kr/help/notice/54590","retrieved":1653628667927},{"title":"김창옥 토크콘서트 시즌2 - 부천 ​​​​​​​​티켓오픈 안내 (티켓링크)","contents":"<em>오픈</em>: 2022.06.02(목) 05:00","link":"http://www.ticketlink.co.kr/help/notice/54589","retrieved":1653628667929},{"title":"2022 변진섭 전국투어 콘서트 : 변천사 - 서울 ​​​​​​​​티켓오픈 안내 (티켓링크)","contents":"<em>오픈</em>: 2022.05.31(화) 05:00","link":"http://www.ticketlink.co.kr/help/notice/54588","retrieved":1653628667930},{"title":"2022 세종솔로이스츠의 힉엣눙크! 갈라 콘서트 ​​​​​​​티켓오픈 안내 (티켓링크)","contents":"<em>오픈</em>: 2022.05.27(금) 02:00","link":"http://www.ticketlink.co.kr/help/notice/54587","retrieved":1653556421421},{"title":"[단독판매] 광주시립국악관현악단 제 129회 정기연주회 `청소년 협연의 밤'​ 티켓오픈 안내 (티켓링크 모바일)","contents":"2022.05.30(월) 01:00","link":"http://m.ticketlink.co.kr/help/notice/54601","retrieved":1653721914648},{"title":"세종 어린이 시리즈 Ⅱ 가족음악극 〈백조마을의 차이콥스키〉 ​​​​​​​​티켓오픈 안내 (티켓링크 모바일)","contents":"2022.06.03(금) 07:00","link":"http://m.ticketlink.co.kr/help/notice/54600","retrieved":1653642875743},{"title":"뮤지컬 〈유진과 유진〉 2차 티켓오픈 안내​ (티켓링크 모바일)","contents":"2022.06.03(금) 06:00","link":"http://m.ticketlink.co.kr/help/notice/54599","retrieved":1653632205216},{"title":"강릉시립합창단 제 107회 정기연주회​ 티켓오픈 안내 (티켓링크 모바일)","contents":"2022.05.30(월) 02:00","link":"http://m.ticketlink.co.kr/help/notice/54598","retrieved":1653632205223},{"title":"[단독판매]   제1회 드림콘서트 트롯 티켓오픈 안내 (티켓링크 모바일)","contents":"2022.05.31(화) 11:00","link":"http://m.ticketlink.co.kr/help/notice/54597","retrieved":1653628677410},{"title":"뮤지컬 〈은밀하게 위대하게：THE LAST〉 마지막 티켓오픈 안내 (티켓링크 모바일)","contents":"2022.05.31(화) 02:00","link":"http://m.ticketlink.co.kr/help/notice/54596","retrieved":1653628677410},{"title":"가족뮤지컬[반짝반짝 달님이의 버블버블 솜사탕] ​​​​​​​​티켓오픈 안내 (티켓링크 모바일)","contents":"2022.05.31(화) 01:00","link":"http://m.ticketlink.co.kr/help/notice/54595","retrieved":1653628677410},{"title":"엘사의 생일파티 - 이천 ​​​​​​​​티켓오픈 안내 (티켓링크 모바일)","contents":"2022.05.31(화) 00:00","link":"http://m.ticketlink.co.kr/help/notice/54594","retrieved":1653628677411},{"title":"헬로카봇 뮤지컬 시즌6 <흔들흔들 댄스파티> - 인천 ​​​​​​​​티켓오픈 안내 (티켓링크 모바일)","contents":"2022.06.02(목) 02:00","link":"http://m.ticketlink.co.kr/help/notice/54593","retrieved":1653628677412},{"title":"엘사의 생일파티 - 서산 ​​​​​​​​티켓오픈 안내 (티켓링크 모바일)","contents":"2022.06.02(목) 00:00","link":"http://m.ticketlink.co.kr/help/notice/54592","retrieved":1653628677414},{"title":"뮤지컬 <타루와리나> ​​​​​​​​티켓오픈 안내 (티켓링크 모바일)","contents":"2022.05.31(화) 05:00","link":"http://m.ticketlink.co.kr/help/notice/54591","retrieved":1653628677415},{"title":"엘사의 생일파티 - 대구 동구 ​​​​​​​​티켓오픈 안내 (티켓링크 모바일)","contents":"2022.06.02(목) 00:00","link":"http://m.ticketlink.co.kr/help/notice/54590","retrieved":1653628677416},{"title":"김창옥 토크콘서트 시즌2 - 부천 ​​​​​​​​티켓오픈 안내 (티켓링크 모바일)","contents":"2022.06.02(목) 05:00","link":"http://m.ticketlink.co.kr/help/notice/54589","retrieved":1653628677418},{"title":"2022 변진섭 전국투어 콘서트 : 변천사 - 서울 ​​​​​​​​티켓오픈 안내 (티켓링크 모바일)","contents":"2022.05.31(화) 05:00","link":"http://m.ticketlink.co.kr/help/notice/54588","retrieved":1653620649875},{"title":"2022 세종솔로이스츠의 힉엣눙크! 갈라 콘서트 ​​​​​​​티켓오픈 안내 (티켓링크 모바일)","contents":"2022.05.27(금) 02:00","link":"http://m.ticketlink.co.kr/help/notice/54587","retrieved":1653620649876}]}