{"title":"티켓링크","url":"http://www.ticketlink.co.kr/help/notice","favicon":"http://tketlink.dn.toastoven.net/ticketlink-cdn/web/TLfavicon.ico","elements":[{"title":"뮤지컬 ＜시카고＞ 25주년 기념 오리지널 내한 - 부산 티켓오픈 안내","contents":"<em>오픈</em>: 2023.05.31(수) 05:00","link":"http://www.ticketlink.co.kr/help/notice/56914","retrieved":1684908798398},{"title":"[단독판매] 광주시립합창단 제193회 정기연주회 ‘선물’ 티켓오픈 안내","contents":"<em>오픈</em>: 2023.05.25(목) 01:00","link":"http://www.ticketlink.co.kr/help/notice/56913","retrieved":1684905006424},{"title":"최고다 호기심딱지 - 창원 티켓오픈 안내","contents":"<em>오픈</em>: 2023.05.26(금) 01:00","link":"http://www.ticketlink.co.kr/help/notice/56912","retrieved":1684894045009},{"title":"최고다 호기심딱지 - 춘천 티켓오픈 안내","contents":"<em>오픈</em>: 2023.05.26(금) 01:00","link":"http://www.ticketlink.co.kr/help/notice/56911","retrieved":1684894045009},{"title":"최고다 호기심딱지 - 익산 티켓오픈 안내","contents":"<em>오픈</em>: 2023.05.26(금) 01:00","link":"http://www.ticketlink.co.kr/help/notice/56910","retrieved":1684894045024},{"title":"연극 <극적인 하룻밤> - 대구 티켓오픈 안내","contents":"<em>오픈</em>: 2023.05.26(금) 00:00","link":"http://www.ticketlink.co.kr/help/notice/56909","retrieved":1684889579388},{"title":"​[단독판매]  카이로스 <댄스 오페라 춤추는 카르멘> - 대구 티켓오픈 안내","contents":"<em>오픈</em>: 2023.05.30(화) 05:00","link":"http://www.ticketlink.co.kr/help/notice/56908","retrieved":1684889579400},{"title":"​[단독판매]  이수희 피아노 리사이틀 - 대구 티켓오픈 안내","contents":"<em>오픈</em>: 2023.05.30(화) 05:00","link":"http://www.ticketlink.co.kr/help/notice/56907","retrieved":1684889579401},{"title":"뮤지컬 데스노트(The Musical Death Note)- 부산​ 티켓오픈 안내","contents":"<em>오픈</em>: 2023.05.30(화) 05:00","link":"http://www.ticketlink.co.kr/help/notice/56906","retrieved":1684894045025},{"title":"NEW 뮤지컬 번개맨 <전설의 시작!> - 서울​ 티켓오픈 안내","contents":"<em>오픈</em>: 2023.06.01(목) 02:00","link":"http://www.ticketlink.co.kr/help/notice/56905","retrieved":1684894045025},{"title":"뮤지컬 <할란카운티> 마지막​ 티켓오픈 안내","contents":"<em>오픈</em>: 2023.05.30(화) 05:00","link":"http://www.ticketlink.co.kr/help/notice/56904","retrieved":1684822753191},{"title":"2023 가족매직쇼 <류엘의 매직콘서트> - 수원 티켓오픈 안내","contents":"<em>오픈</em>: 2023.05.25(목) 00:00","link":"http://www.ticketlink.co.kr/help/notice/56903","retrieved":1684818583038},{"title":"​가족뮤지컬 [바다탐험대 옥토넛 시즌2] - 서울 (강서구민회관)​ 티켓오픈 안내","contents":"<em>오픈</em>: 2023.05.25(목) 02:00","link":"http://www.ticketlink.co.kr/help/notice/56902","retrieved":1684811451060},{"title":"​[단독판매]  이바노-프란키브스크 필하모닉 쳄버 “콰트로 코르데”​ 티켓오픈 안내","contents":"<em>오픈</em>: 2023.05.25(목) 05:00","link":"http://www.ticketlink.co.kr/help/notice/56901","retrieved":1684807665886},{"title":"2023 라이브 가족뮤지컬 <미녀와야수> - 부산 티켓오픈 안내","contents":"<em>오픈</em>: 2023.05.24(수) 00:00","link":"http://www.ticketlink.co.kr/help/notice/56900","retrieved":1684807665894}]}