{"title":"티켓링크","url":"http://www.ticketlink.co.kr/help/notice","favicon":"http://tketlink.dn.toastoven.net/ticketlink-cdn/web/TLfavicon.ico","elements":[{"title":"[단독판매]  ​연극 “비평가 (El critico)” - 대구​ 티켓오픈 안내","contents":"<em>오픈</em>: 2024.02.21(수) 01:00","link":"http://www.ticketlink.co.kr/help/notice/58811","retrieved":1708323236201},{"title":"[단독판매] [광주시립교향악단] 382회 정기연주회 ‘Klimax’ 티켓오픈 안내","contents":"<em>오픈</em>: 2024.02.21(수) 08:00","link":"http://www.ticketlink.co.kr/help/notice/58810","retrieved":1708319478641},{"title":"피아노 배틀​ 티켓오픈 안내","contents":"<em>오픈</em>: 2024.02.21(수) 05:00","link":"http://www.ticketlink.co.kr/help/notice/58809","retrieved":1708319478642},{"title":"2024 YB TOUR LIGHTS ; INFINITY  - 원주​ 티켓오픈 안내","contents":"<em>오픈</em>: 2024.02.22(목) 09:00","link":"http://www.ticketlink.co.kr/help/notice/58806","retrieved":1708319478645},{"title":"연극<비클래스> 2차​ 티켓오픈 안내","contents":"<em>오픈</em>: 2024.02.23(금) 06:00","link":"http://www.ticketlink.co.kr/help/notice/58805","retrieved":1708319478647},{"title":"조희창의[토요∙클래식∙살롱] - ll 티켓오픈 안내","contents":"<em>오픈</em>: 2024.02.26(월) 01:00","link":"http://www.ticketlink.co.kr/help/notice/58803","retrieved":1708319478648},{"title":"가족뮤지컬 레인보우 버블젬<흩어진 버블젬을 찾아라!> - 용산 티켓오픈 안내","contents":"<em>오픈</em>: 2024.02.21(수) 05:00","link":"http://www.ticketlink.co.kr/help/notice/58802","retrieved":1708319478650},{"title":"가족뮤지컬 레인보우 버블젬<흩어진 버블젬을 찾아라!> - 구로 티켓오픈 안내","contents":"<em>오픈</em>: 2024.02.21(수) 05:00","link":"http://www.ticketlink.co.kr/help/notice/58801","retrieved":1708319478651},{"title":"뽀로로 20주년 스페셜 매직 싱어롱쇼 <슈퍼스타 뽀로로 드림콘서트> 시즌 2 - 안성 티켓오픈 안내","contents":"<em>오픈</em>: 2024.02.23(금) 02:00","link":"http://www.ticketlink.co.kr/help/notice/58800","retrieved":1708315937852},{"title":"뽀로로 20주년 스페셜 매직 싱어롱쇼 <슈퍼스타 뽀로로 드림콘서트> 시즌 2 - 청주 티켓오픈 안내","contents":"<em>오픈</em>: 2024.02.23(금) 02:00","link":"http://www.ticketlink.co.kr/help/notice/58799","retrieved":1708315937852},{"title":"인피니티 플라잉 - 경주 티켓오픈 안내","contents":"<em>오픈</em>: 2024.02.21(수) 00:00","link":"http://www.ticketlink.co.kr/help/notice/58798","retrieved":1708303444345},{"title":"뮤지컬 한글용사 아이야 <사라진 한글을 찾아라!> - 용인 티켓오픈 안내","contents":"<em>오픈</em>: 2024.02.21(수) 00:00","link":"http://www.ticketlink.co.kr/help/notice/58797","retrieved":1708303444345},{"title":"[단독판매] 대구시민오케스트라 정기연주회 <봄날의 클래식 그리고..> - 대구 티켓오픈 안내","contents":"<em>오픈</em>: 2024.02.21(수) 00:00","link":"http://www.ticketlink.co.kr/help/notice/58796","retrieved":1708303444346},{"title":"어린이마술쇼-김해 티켓오픈 안내","contents":"<em>오픈</em>: 2024.02.21(수) 00:00","link":"http://www.ticketlink.co.kr/help/notice/58795","retrieved":1708303444346},{"title":"그림이 오감를 만났을때 \"감각주의\" - 대구 티켓오픈 안내","contents":"<em>오픈</em>: 2024.03.04(월) 01:00","link":"http://www.ticketlink.co.kr/help/notice/58794","retrieved":1708303444347}]}