{"title":"티켓링크 모바일","url":"http://m.ticketlink.co.kr/help/notice","favicon":"http://tketlink.dn.toastoven.net/ticketlink-cdn/web/TLfavicon.ico","elements":[{"title":"[단독판매] AGAIN ATOM_POP UP Store in 대구 (아톰 팝업스토어 - 대구) ​​ 티켓오픈 안내","contents":"2024.09.13(금) 01:00","link":"http://m.ticketlink.co.kr/help/notice/60279","retrieved":1726016193296},{"title":"[단독판매][광주예술의전당] One, 나의 유토피아​ 티켓오픈 안내","contents":"2024.09.12(목) 07:00","link":"http://m.ticketlink.co.kr/help/notice/60278","retrieved":1725963214330},{"title":"​[단독판매]  별 헤는 밤 빼앗긴 들에서 꽃처럼 침묵을 깨다-군산​ 티켓오픈 안내","contents":"2024.09.11(수) 05:00","link":"http://m.ticketlink.co.kr/help/notice/60277","retrieved":1725956182912},{"title":"국내최정상의 성악가와 함께하는 구노의 ‘장엄미사곡’ 연주회 - 대구 티켓오픈 안내","contents":"2024.09.12(목) 00:00","link":"http://m.ticketlink.co.kr/help/notice/60276","retrieved":1725956182913},{"title":"<11월의 봄> 정훈희x송창식with 함춘호 콘서트 - 대구 티켓오픈 안내","contents":"2024.09.12(목) 05:00","link":"http://m.ticketlink.co.kr/help/notice/60275","retrieved":1725945196504},{"title":"[단독판매]  [경남 청년콘서트] Busker To Stage2 티켓오픈 안내","contents":"2024.09.11(수) 05:00","link":"http://m.ticketlink.co.kr/help/notice/60274","retrieved":1725941685323},{"title":"​[고양] 뮤지컬 캐치! 티니핑 <두근두근 싱어롱 콘서트!>​ 티켓오픈 안내","contents":"2024.09.12(목) 05:00","link":"http://m.ticketlink.co.kr/help/notice/60273","retrieved":1725945196507},{"title":"GUMMY Tour Concert 2024 < LOVE >-청주 티켓오픈 안내","contents":"2024.09.12(목) 07:00","link":"http://m.ticketlink.co.kr/help/notice/60272","retrieved":1725934229934},{"title":"GUMMY Tour Concert 2024 < LOVE >-광주 티켓오픈 안내","contents":"2024.09.12(목) 06:00","link":"http://m.ticketlink.co.kr/help/notice/60271","retrieved":1725934229939},{"title":"GUMMY Tour Concert 2024 < LOVE >-전주 티켓오픈 안내","contents":"2024.09.12(목) 05:00","link":"http://m.ticketlink.co.kr/help/notice/60270","retrieved":1725934229940},{"title":"사라 장 바이올린 리사이틀 - 청주​ 티켓오픈 안내","contents":"2024.09.12(목) 02:00","link":"http://m.ticketlink.co.kr/help/notice/60269","retrieved":1725934229940},{"title":"가족뮤지컬 마법여우 주비 “신비한 칠교 목걸이의 비밀” - 부천​ 티켓오픈 안내","contents":"2024.09.13(금) 01:00","link":"http://m.ticketlink.co.kr/help/notice/60268","retrieved":1725934229944},{"title":"(2024 롯데백화점 대구) 산타와 루돌프​ 티켓오픈 안내","contents":"2024.09.13(금) 00:00","link":"http://m.ticketlink.co.kr/help/notice/60267","retrieved":1725934229944},{"title":"2024 어썸스테이지 [ N.Flying ] 티켓오픈 안내","contents":"2024.09.12(목) 11:00","link":"http://m.ticketlink.co.kr/help/notice/60266","retrieved":1725929805814},{"title":"2024 어썸스테이지 [ 로이킴 X 임현식(BTOB) ] 티켓오픈 안내","contents":"2024.09.12(목) 11:00","link":"http://m.ticketlink.co.kr/help/notice/60265","retrieved":1725929805815}]}