{"title":"티켓링크 모바일","url":"http://m.ticketlink.co.kr/help/notice","favicon":"http://tketlink.dn.toastoven.net/ticketlink-cdn/web/TLfavicon.ico","elements":[{"title":"2025 폴포츠 내한 공연 : Prime Time - 김해​ 티켓오픈 안내","contents":"2025.02.07(금) 02:00","link":"http://m.ticketlink.co.kr/help/notice/61302","retrieved":1738660426133},{"title":"2025 폴포츠 내한 공연 : Prime Time - 안성​ 티켓오픈 안내","contents":"2025.02.07(금) 02:00","link":"http://m.ticketlink.co.kr/help/notice/61301","retrieved":1738660426135},{"title":"2025 세종시즌​​ 티켓오픈 안내","contents":"2025.02.06(목) 01:00","link":"http://m.ticketlink.co.kr/help/notice/61300","retrieved":1738660426146},{"title":"2025 노을 발렌타인데이 콘서트 'Sunset Love: Valentine Special'​ 티켓오픈 안내","contents":"2025.02.06(목) 10:00","link":"http://m.ticketlink.co.kr/help/notice/61299","retrieved":1738660426146},{"title":"어린이 마술극 <리온의 신비한 과자상점>(3월) - 부산​ 티켓오픈 안내","contents":"2025.02.05(수) 00:00","link":"http://m.ticketlink.co.kr/help/notice/61298","retrieved":1738653170919},{"title":"뮤지컬 <사랑의 하츄핑> - 대구​ 티켓오픈 안내","contents":"2025.02.06(목) 05:00","link":"http://m.ticketlink.co.kr/help/notice/61297","retrieved":1738653170921},{"title":"뮤지컬 <명성황후> 30주년 기념 공연 - 용인 티켓오픈 안내","contents":"2025.02.07(금) 05:00","link":"http://m.ticketlink.co.kr/help/notice/61296","retrieved":1738653170933},{"title":"로맨틱 화이트데이 디너 콘서트 티켓오픈 안내","contents":"2025.02.06(목) 01:00","link":"http://m.ticketlink.co.kr/help/notice/61295","retrieved":1738649901337},{"title":"2025 변진섭 전국투어 콘서트 : 변천사 시즌2 더가까이 - 서울​​​ 티켓오픈 안내","contents":"2025.02.07(금) 02:00","link":"http://m.ticketlink.co.kr/help/notice/61294","retrieved":1738645960920},{"title":"​2025 이승철 콘서트 <오케스트락2> 이천공연​​ 티켓오픈 안내","contents":"2025.02.07(금) 05:00","link":"http://m.ticketlink.co.kr/help/notice/61293","retrieved":1738657020002},{"title":"[단독판매] 나상현씨밴드 단독콘서트 '심화과정 2025' 티켓오픈 안내","contents":"2025.02.07(금) 10:00","link":"http://m.ticketlink.co.kr/help/notice/61292","retrieved":1738638941357},{"title":"가족뮤지컬 <고고다이노 - 해양구조대> - 청주​ 티켓오픈 안내","contents":"2025.02.07(금) 00:00","link":"http://m.ticketlink.co.kr/help/notice/61291","retrieved":1738635207741},{"title":"[단독판매]  2025 어썸스테이지 [ Xdinary Heroes x YdBB​ ]​​ 티켓오픈 안내","contents":"2025.02.07(금) 11:00","link":"http://m.ticketlink.co.kr/help/notice/61290","retrieved":1738577653038},{"title":"[단독판매]  2025 어썸스테이지 [ Xdinary Heroes x HANRORO ]​​ 티켓오픈 안내","contents":"2025.02.07(금) 10:00","link":"http://m.ticketlink.co.kr/help/notice/61289","retrieved":1738577653040},{"title":"[단독판매]  2025 어썸스테이지 [ Xdinary Heroes x ONEWE ]​​ 티켓오픈 안내","contents":"2025.02.06(목) 11:00","link":"http://m.ticketlink.co.kr/help/notice/61288","retrieved":1738577653044}]}