{"title":"티켓링크","url":"http://www.ticketlink.co.kr/help/notice","favicon":"http://tketlink.dn.toastoven.net/web/AOS.ico","elements":[{"title":"가족뮤지컬 〈반짝반짝 달님이 - 버블버블 마법의 솜사탕〉 - 부산 티켓오픈 안내","contents":"<em>오픈</em>: 2022.07.07(목) 01:00","link":"http://www.ticketlink.co.kr/help/notice/54833","retrieved":1657008912223},{"title":"2022 뮤지컬 <미드나잇 : 액터뮤지션> 하반기 1차 티켓오픈 안내","contents":"<em>오픈</em>: 2022.07.11(월) 05:00","link":"http://www.ticketlink.co.kr/help/notice/54832","retrieved":1657008912223},{"title":"〈뉴페스타〉 2022 블라인드 티켓오픈 안내","contents":"<em>오픈</em>: 2022.07.06(수) 05:00","link":"http://www.ticketlink.co.kr/help/notice/54831","retrieved":1657008912224},{"title":"2022 서울시뮤지컬단 뮤지컬 〈원더보이〉​ 티켓오픈 안내","contents":"<em>오픈</em>: 2022.07.06(수) 05:00","link":"http://www.ticketlink.co.kr/help/notice/54830","retrieved":1656995519946},{"title":"광주시립국악관현악단 제 130회 정기연주회 ‘신나는 국악여행’ 티켓오픈 안내","contents":"<em>오픈</em>: 2022.07.06(수) 02:00","link":"http://www.ticketlink.co.kr/help/notice/54829","retrieved":1656995519956},{"title":"[단독판매] 2022 N.FLYING(엔플라잉) LIVE ‘&CON2’ - 대구 티켓오픈 안내","contents":"<em>오픈</em>: 2022.07.08(금) 12:00","link":"http://www.ticketlink.co.kr/help/notice/54828","retrieved":1656929652421},{"title":"[단독판매] 2022 N.FLYING(엔플라잉) LIVE ‘&CON2’ - 부산 티켓오픈 안내","contents":"<em>오픈</em>: 2022.07.08(금) 11:00","link":"http://www.ticketlink.co.kr/help/notice/54827","retrieved":1656929652425},{"title":"HAUS OF WONDER 3차 일반예매 티켓오픈 안내","contents":"<em>오픈</em>: 2022.07.04(월) 09:00","link":"http://www.ticketlink.co.kr/help/notice/54826","retrieved":1656923134581},{"title":"앤서니브라운의 돼지책 - 당진 티켓오픈 안내","contents":"<em>오픈</em>: 2022.07.05(화) 00:00","link":"http://www.ticketlink.co.kr/help/notice/54825","retrieved":1656923134582},{"title":"앤서니브라운의 돼지책 - 파주 티켓오픈 안내","contents":"<em>오픈</em>: 2022.07.06(수) 00:00","link":"http://www.ticketlink.co.kr/help/notice/54824","retrieved":1656923134584},{"title":"앤서니브라운의 돼지책 - 서울 노원 티켓오픈 안내","contents":"<em>오픈</em>: 2022.07.06(수) 00:00","link":"http://www.ticketlink.co.kr/help/notice/54823","retrieved":1656923134585},{"title":"2022 김동현, 이솔로몬 조인콘서트 – 제주​ 티켓오픈 안내","contents":"<em>오픈</em>: 2022.07.08(금) 05:00","link":"http://www.ticketlink.co.kr/help/notice/54822","retrieved":1656923134588},{"title":"[뮤지컬 더데빌 콘서트] 티켓 오픈 안내","contents":"<em>오픈</em>: 2022.07.08(금) 05:00","link":"http://www.ticketlink.co.kr/help/notice/54821","retrieved":1656923134588},{"title":"뮤지컬 〈​미세스 다웃파이어〉​ 1차​ 티켓오픈 안내","contents":"<em>오픈</em>: 2022.07.07(목) 05:00","link":"http://www.ticketlink.co.kr/help/notice/54820","retrieved":1656923134589},{"title":"연극 〈​빈센트 리버〉​ 2차​ 티켓오픈 안내","contents":"<em>오픈</em>: 2022.07.08(금) 06:00","link":"http://www.ticketlink.co.kr/help/notice/54819","retrieved":1656923134592}]}